django_workspaces/__init__.py
django_workspaces/_compat.py
django_workspaces/apps.py
django_workspaces/middleware.py
django_workspaces/models.py
django_workspaces/py.typed
django_workspaces/signals.py
django_workspaces/types.py
django_workspaces/migrations/0001_initial.py
django_workspaces/migrations/__init__.py
django_workspaces-0.0.1a1.dist-info/METADATA
django_workspaces-0.0.1a1.dist-info/WHEEL
django_workspaces-0.0.1a1.dist-info/licenses/LICENSE.txt
django_workspaces-0.0.1a1.dist-info/RECORD
